bakerstreet/__init__.py
bakerstreet/bakerstreet.pb.go
bakerstreet/bakerstreet.proto
bakerstreet/bakerstreet_grpc.pb.go
bakerstreet/bakerstreet_pb2.py
bakerstreet/bakerstreet_pb2_grpc.py
bakerstreet-2.2.0.dist-info/METADATA
bakerstreet-2.2.0.dist-info/WHEEL
bakerstreet-2.2.0.dist-info/licenses/LICENSE
bakerstreet-2.2.0.dist-info/RECORD
