Metadata-Version: 2.3
Name: bakerstreet
Version: 2.2.0
Summary: The place where most characters meet. RPC defnition for our services
Project-URL: Repository, https://github.com/appknox/bakerstreet
Project-URL: Releases, https://github.com/appknox/bakerstreet/releases
Author-email: Appknox <engineering@appknox.com>
License: MIT License
Keywords: appknox,bakerstreet,rpc
Requires-Python: >=3.12
Requires-Dist: grpcio>=1.68.1
Requires-Dist: protobuf>=5.29.1
